.gitignore
LICENSE
README.md
setup.py
transmile.py
example/.gitignore
example/Makefile
example/dist/src/._example.sml.mlb
example/dist/src/._stack.sig.mlb
example/dist/src/._stack.sml.mlb
example/dist/src/example.sml
example/dist/src/example.sml.mlb
example/dist/src/stack.sig
example/dist/src/stack.sig.mlb
example/dist/src/stack.sml
example/dist/src/stack.sml.mlb
example/src/example.smlb
example/src/stack.sigb
example/src/stack.smlb
example/vanilla/example.mlb
example/vanilla/example.sml
example/vanilla/stack.sig
example/vanilla/stack.sml
transmler/.gitignore
transmler/__init__.py
transmler/__main__.py
transmler/cli.py
transmler/parser.py
transmler/run.py
transmler.egg-info/PKG-INFO
transmler.egg-info/SOURCES.txt
transmler.egg-info/dependency_links.txt
transmler.egg-info/entry_points.txt
transmler.egg-info/top_level.txt