Metadata-Version: 1.2
Name: transmler
Version: 0.3
Summary: syntactic sugar for MLBasis files
Home-page: https://github.com/myegorov/transmler
Author: Maksim Yegorov
Author-email: findmaksim@gmail.com
License: MIT
Keywords: transpiler sml mlton import export
Platform: UNKNOWN
Classifier: Development Status :: 4 - Beta
Classifier: License :: OSI Approved :: MIT License
Classifier: Programming Language :: Python :: 3
Classifier: Topic :: Software Development :: Build Tools
Classifier: Intended Audience :: Developers
Requires-Python: >=3.0
